<?xml version='1.0' encoding='UTF-8'?>
<package uuid="-32a3c0" version="0.0.0">
 <names>
  <name lang="en_US">TapperSample</name>
 </names>
 <supportedLanguages>
  <language>ja_JP</language>
 </supportedLanguages>
 <descriptionLanguages>
  <language>ja_JP</language>
 </descriptionLanguages>
 <contents>
  <behaviorContent path=".">
   <userRequestable/>
   <nature>interactive</nature>
   <permissions/>
  </behaviorContent>
  <behaviorContent path="behavior_2">
   <nature>interactive</nature>
   <permissions/>
  </behaviorContent>
  <behaviorContent path="behavior_1">
   <nature>interactive</nature>
   <permissions/>
  </behaviorContent>
 </contents>
</package>
